mysql_partition/__init__.py
mysql_partition/mysql_partition.py
mysql_partition-1.0.2.dist-info/METADATA
mysql_partition-1.0.2.dist-info/WHEEL
mysql_partition-1.0.2.dist-info/top_level.txt
mysql_partition-1.0.2.dist-info/RECORD
