Metadata-Version: 2.1
Name: mysql_partition
Version: 1.0.2
Summary: This library provides functions for querying the latest partitions of MySQL database partition tables and creating table partitions.
Author-email: lytcreate <lytcreate@163.com>
Classifier: Programming Language :: Python :: 3
Classifier: License :: OSI Approved :: MIT License
Requires-Python: >=3.0
